osxharvey/__init__.py
osxharvey/__main__.py
osxharvey/_version.py
osxharvey/dot11_packet_handler.py
osxharvey/event.py
osxharvey/main.py
osxharvey/tests/__init__.py
osxharvey/tests/osxharvey_test.py
osxharvey-0.0.11.dist-info/LICENSE.md
osxharvey-0.0.11.dist-info/METADATA
osxharvey-0.0.11.dist-info/WHEEL
osxharvey-0.0.11.dist-info/entry_points.txt
osxharvey-0.0.11.dist-info/top_level.txt
osxharvey-0.0.11.dist-info/RECORD
