Metadata-Version: 2.1
Name: osxharvey
Version: 0.0.11
Summary: Big White Rabbit, which can hop wifi channels while sniffing for information
Home-page: https://github.com/kampfhamster309/osxharvey
Author: Felix Harenbrock
Author-email: felix.harenbrock@gmx.de
License: MIT
Download-URL: https://pypi.org/project/osxharvey/
Project-URL: Bug Tracker, https://github.com/kampfhamster309/osxharvey/issues
Keywords: OSX Sniffer,Channel Hopping,Wifi Sniffer,Wifi Sniffer Mac
Platform: UNKNOWN
Classifier: Development Status :: 2 - Pre-Alpha
Classifier: Intended Audience :: Developers
Classifier: License :: OSI Approved :: MIT License
Classifier: Operating System :: MacOS
Classifier: Programming Language :: Python :: 3
Classifier: Topic :: Security
Requires-Dist: ouilookup (>=0.2.4)
Requires-Dist: protobuf (>=3.15.4)
Requires-Dist: scapy (>=2.4.5)
Requires-Dist: six (>=1.15.0)
Requires-Dist: tqdm (>=4.61.0)
